rework/__init__.py
rework/api.py
rework/cli.py
rework/helper.py
rework/io.py
rework/monitor.py
rework/schema.py
rework/schema.sql
rework/task.py
rework/testutils.py
rework/worker.py
rework-0.17.2.dist-info/METADATA
rework-0.17.2.dist-info/WHEEL
rework-0.17.2.dist-info/entry_points.txt
rework-0.17.2.dist-info/top_level.txt
rework-0.17.2.dist-info/RECORD
